LICENSE
MANIFEST.in
README.md
setup.cfg
setup.py
data/campus.dbf
data/campus.shp
data/campus.shx
s2g/__init__.py
s2g/bonus.py
s2g/shapegraph.py
s2g.egg-info/PKG-INFO
s2g.egg-info/SOURCES.txt
s2g.egg-info/dependency_links.txt
s2g.egg-info/requires.txt
s2g.egg-info/top_level.txt
tests/test.py