Metadata-Version: 1.1
Name: s2g
Version: 0.2.3
Summary: Shapefile to graph/network converter in Python
Home-page: https://github.com/caesar0301/python-s2g
Author: Xiaming Chen
Author-email: chenxm35@gmail.com
License: MIT
Keywords: shapefile,graph,network,GIS
Platform: UNKNOWN
Classifier: Development Status :: 4 - Beta
Classifier: Environment :: Console
Classifier: Intended Audience :: Developers
Classifier: License :: Freely Distributable
Classifier: Operating System :: OS Independent
Classifier: Programming Language :: Python
Classifier: Programming Language :: Python :: 2.6
Classifier: Programming Language :: Python :: 2.7
Classifier: Programming Language :: Python :: 3.2
Classifier: Programming Language :: Python :: 3.3
Classifier: Programming Language :: Python :: 3.4
Classifier: Programming Language :: Python :: 3.5
Classifier: Topic :: Software Development :: Libraries :: Python Modules
